pydoll_substack2md/__init__.py
pydoll_substack2md/pydoll_scraper.py
substack2md-0.1.1.dist-info/licenses/LICENSE
substack2md-0.1.1.dist-info/METADATA
substack2md-0.1.1.dist-info/WHEEL
substack2md-0.1.1.dist-info/entry_points.txt
substack2md-0.1.1.dist-info/top_level.txt
substack2md-0.1.1.dist-info/RECORD
