Metadata-Version: 2.4
Name: substack2md
Version: 0.1.1
Summary: A CAPTCHA-safe Python scraper with Cloudflare bypass that downloads Substack posts and converts them to Markdown. Features automatic CAPTCHA solving, human-like scraping delays, and respectful rate limiting.
Author-email: cognitive-glitch <drivedon02@gmail.com>
License: MIT
Project-URL: Homepage, https://github.com/cognitive-glitch/pydoll-substack2md
Project-URL: Bug Tracker, https://github.com/cognitive-glitch/pydoll-substack2md/issues
Project-URL: Documentation, https://github.com/cognitive-glitch/pydoll-substack2md#readme
Keywords: substack,scraper,markdown,newsletter,pydoll,async,cloudflare-bypass,captcha,anti-bot,web-scraping
Classifier: Development Status :: 4 - Beta
Classifier: Intended Audience :: Developers
Classifier: License :: OSI Approved :: MIT License
Classifier: Programming Language :: Python :: 3
Classifier: Programming Language :: Python :: 3.10
Classifier: Programming Language :: Python :: 3.11
Classifier: Programming Language :: Python :: 3.12
Classifier: Programming Language :: Python :: 3.13
Classifier: Topic :: Internet :: WWW/HTTP :: Dynamic Content
Classifier: Topic :: Software Development :: Libraries :: Python Modules
Requires-Python: >=3.10
License-File: LICENSE
Requires-Dist: pydoll-python>=2.2
Requires-Dist: html-to-markdown>=1.3
Requires-Dist: beautifulsoup4>=4.12
Requires-Dist: lxml>=5.0
Requires-Dist: tqdm>=4.66
Requires-Dist: requests>=2.31.0
Requires-Dist: markdown>=3.6
Requires-Dist: python-dotenv>=1.0.0
Requires-Dist: python-dateutil>=2.8.0
Provides-Extra: dev
Requires-Dist: pytest>=8.0; extra == "dev"
Requires-Dist: pytest-asyncio>=1.0; extra == "dev"
Requires-Dist: black>=25.0.0; extra == "dev"
Requires-Dist: ruff>=0.1.0; extra == "dev"
Requires-Dist: pyright>=1.1.345; extra == "dev"
Requires-Dist: ty; extra == "dev"
Dynamic: license-file
